pipeline_flow/__init__.py
pipeline_flow/common/__init__.py
pipeline_flow/common/exceptions.py
pipeline_flow/common/type_def.py
pipeline_flow/common/utils/__init__.py
pipeline_flow/common/utils/helpers.py
pipeline_flow/common/utils/logger.py
pipeline_flow/common/utils/validation.py
pipeline_flow/core/__init__.py
pipeline_flow/core/executor.py
pipeline_flow/core/models/__init__.py
pipeline_flow/core/models/phases.py
pipeline_flow/core/models/pipeline.py
pipeline_flow/core/orchestrator.py
pipeline_flow/core/parsers/__init__.py
pipeline_flow/core/parsers/pipeline_parser.py
pipeline_flow/core/parsers/plugin_parser.py
pipeline_flow/core/parsers/secret_parser.py
pipeline_flow/core/parsers/yaml_parser.py
pipeline_flow/core/plugin_loader.py
pipeline_flow/core/registry.py
pipeline_flow/entrypoint.py
pipeline_flow/plugins/__init__.py
pipeline_flow/plugins/base.py
pipeline_flow/plugins/extract/__init__.py
pipeline_flow/plugins/extract/rest_api_async.py
pipeline_flow/plugins/load/__init__.py
pipeline_flow/plugins/load/sqlalchemy_query_async.py
pipeline_flow/plugins/merge/__init__.py
pipeline_flow/plugins/secret_managers/__init__.py
pipeline_flow/plugins/secret_managers/aws_secret_manager.py
pipeline_flow/plugins/transform/__init__.py
pipeline_flow/plugins/transform/native.py
pipeline_flow/plugins/transform/pyspark.py
pipeline_flow/plugins/utility/__init__.py
pipeline_flow/plugins/utility/pagination.py
pipeline_flow-1.0.8.dist-info/LICENSE
pipeline_flow-1.0.8.dist-info/METADATA
pipeline_flow-1.0.8.dist-info/WHEEL
pipeline_flow-1.0.8.dist-info/RECORD
