Metadata-Version: 2.3
Name: pipeline-flow
Version: 1.0.8
Summary: A framework for building ETL, ELT and ETLT data pipelines dynamically using plugins.
License: BSD-3-Clause
Keywords: ETL,ELT,ETLT,data pipelines,plugins,asyncio,data engineering
Author: Jakub Pulaczewski
Author-email: jakub.pulaczewski@example.com
Maintainer: Jakub Pulaczewski
Maintainer-email: jakub.pulaczewski@example.com
Requires-Python: >=3.12,<4.0
Classifier: License :: OSI Approved :: BSD License
Classifier: Programming Language :: Python :: 3
Classifier: Programming Language :: Python :: 3.12
Classifier: Programming Language :: Python :: 3.13
Requires-Dist: aiofiles (>=24.1.0,<25.0.0)
Requires-Dist: asyncmy (>=0.2.10,<0.3.0)
Requires-Dist: boto3 (>=1.36.21,<2.0.0)
Requires-Dist: cryptography (>=44.0.1,<45.0.0)
Requires-Dist: httpx (>=0.28.1,<0.29.0)
Requires-Dist: pydantic (>=2.4.2,<3.0.0)
Requires-Dist: returns (>=0.24.0,<0.25.0)
Requires-Dist: sqlalchemy[asyncio] (>=2.0.38,<3.0.0)
Requires-Dist: tenacity (>=9.0.0,<10.0.0)
Requires-Dist: yamlcore (>=0.0.4,<0.0.5)
Project-URL: Homepage, http://pipeline-flow.readthedocs.io/
Project-URL: Repository, https://github.com/jakubpulaczewski/pipeline-flow
